gnatss/__init__.py
gnatss/__main__.py
gnatss/cli.py
gnatss/constants.py
gnatss/loaders.py
gnatss/main.py
gnatss/version.py
gnatss/configs/__init__.py
gnatss/configs/io.py
gnatss/configs/main.py
gnatss/configs/posfilter.py
gnatss/configs/solver.py
gnatss/configs/transponders.py
gnatss/dataspec/__init__.py
gnatss/dataspec/base.py
gnatss/dataspec/utils.py
gnatss/dataspec/v1.py
gnatss/ops/__init__.py
gnatss/ops/data.py
gnatss/ops/harmonic_mean.py
gnatss/ops/io.py
gnatss/ops/kalman.py
gnatss/ops/qc.py
gnatss/ops/utils.py
gnatss/ops/validate.py
gnatss/posfilter/__init__.py
gnatss/posfilter/posfilter.py
gnatss/posfilter/run.py
gnatss/posfilter/utilities.py
gnatss/solver/__init__.py
gnatss/solver/methods.py
gnatss/solver/run.py
gnatss/solver/solve.py
gnatss/solver/utilities.py
gnatss/utilities/__init__.py
gnatss/utilities/geo.py
gnatss/utilities/io.py
gnatss/utilities/testing.py
gnatss/utilities/time.py
gnatss-0.3.1.dist-info/METADATA
gnatss-0.3.1.dist-info/WHEEL
gnatss-0.3.1.dist-info/entry_points.txt
gnatss-0.3.1.dist-info/licenses/LICENSE
gnatss-0.3.1.dist-info/RECORD
