Metadata-Version: 2.4
Name: gnatss
Version: 0.3.1
Summary: Community Seafloor Global Navigation Satellite Systems - Acoustic (GNSS-A) Transponder Surveying Software
Project-URL: Homepage, https://github.com/seafloor-geodesy/gnatss
Project-URL: Documentation, https://gnatss.readthedocs.io
Project-URL: Repository, https://github.com/seafloor-geodesy/gnatss.git
Project-URL: Issues, https://github.com/seafloor-geodesy/gnatss/issues
License: BSD 3-Clause License
License-File: LICENSE
Classifier: Development Status :: 3 - Alpha
Classifier: Intended Audience :: Developers
Classifier: License :: OSI Approved :: BSD License
Classifier: Operating System :: OS Independent
Classifier: Programming Language :: Python :: 3.10
Classifier: Programming Language :: Python :: 3.11
Classifier: Topic :: Scientific/Engineering
Classifier: Topic :: Software Development :: Build Tools
Classifier: Topic :: Software Development :: Libraries :: Python Modules
Requires-Python: >=3.10
Requires-Dist: astropy<8,>=6.1.7
Requires-Dist: cftime<2,>=1.6.2
Requires-Dist: fsspec<2025,>=2024.5.0
Requires-Dist: matplotlib<4,>=3.8.0
Requires-Dist: nptyping<3,>=2.5.0
Requires-Dist: numba<1,>=0.56.4
Requires-Dist: numpy<2,>1.26
Requires-Dist: pandas<3,>=2.0.3
Requires-Dist: pluggy<2,>=1.2.0
Requires-Dist: pydantic-settings<3,>=2.0.3
Requires-Dist: pydantic==2.8.2
Requires-Dist: pymap3d<4,>=3.0.1
Requires-Dist: pyproj<4,>=3.5.0
Requires-Dist: pyyaml<7,>=6.0.1
Requires-Dist: scipy<2,>=1.10.1
Requires-Dist: typer<1,>=0.7.0
Requires-Dist: xarray<2025,>=2024.5.0
Provides-Extra: all
Requires-Dist: autodoc-pydantic<3.0,>=2.0.1; extra == 'all'
Requires-Dist: hypothesis; extra == 'all'
Requires-Dist: jupyter-book; extra == 'all'
Requires-Dist: meson; extra == 'all'
Requires-Dist: ninja>1.8.2; extra == 'all'
Requires-Dist: nox; extra == 'all'
Requires-Dist: numpydoc; extra == 'all'
Requires-Dist: pre-commit; extra == 'all'
Requires-Dist: pygithub; extra == 'all'
Requires-Dist: pytest; extra == 'all'
Requires-Dist: pytest-benchmark; extra == 'all'
Requires-Dist: pytest-cov; extra == 'all'
Requires-Dist: pytest-flake8; extra == 'all'
Requires-Dist: pytest-mock; extra == 'all'
Requires-Dist: pytest-xdist; extra == 'all'
Requires-Dist: sphinx-automodapi; extra == 'all'
Requires-Dist: sphinx-panels; extra == 'all'
Requires-Dist: sphinx-rtd-theme; extra == 'all'
Requires-Dist: sphinxcontrib-mermaid; extra == 'all'
Provides-Extra: docs
Requires-Dist: autodoc-pydantic<3.0,>=2.0.1; extra == 'docs'
Requires-Dist: jupyter-book; extra == 'docs'
Requires-Dist: numpydoc; extra == 'docs'
Requires-Dist: sphinx-automodapi; extra == 'docs'
Requires-Dist: sphinx-panels; extra == 'docs'
Requires-Dist: sphinx-rtd-theme; extra == 'docs'
Requires-Dist: sphinxcontrib-mermaid; extra == 'docs'
Provides-Extra: test
Requires-Dist: hypothesis; extra == 'test'
Requires-Dist: meson; extra == 'test'
Requires-Dist: ninja>1.8.2; extra == 'test'
Requires-Dist: nox; extra == 'test'
Requires-Dist: pre-commit; extra == 'test'
Requires-Dist: pygithub; extra == 'test'
Requires-Dist: pytest; extra == 'test'
Requires-Dist: pytest-benchmark; extra == 'test'
Requires-Dist: pytest-cov; extra == 'test'
Requires-Dist: pytest-flake8; extra == 'test'
Requires-Dist: pytest-mock; extra == 'test'
Requires-Dist: pytest-xdist; extra == 'test'
